setup.py
valhallapy/__init__.py
valhallapy/valhalla.py
valhallapy.egg-info/PKG-INFO
valhallapy.egg-info/SOURCES.txt
valhallapy.egg-info/dependency_links.txt
valhallapy.egg-info/not-zip-safe
valhallapy.egg-info/requires.txt
valhallapy.egg-info/top_level.txt