Metadata-Version: 1.0
Name: valhallapy
Version: 0.1.2
Summary: Python Wrapper for the MapZen's routing engine Valhalla 
Home-page: http://github.com/stuartlynn/valhallapy
Author: Stuart Lynn
Author-email: slynn@cartodb.com
License: MIT
Platform: UNKNOWN
